{"cameraMode":{"drawMode":0,"name":"Shaded","section":"Shading Mode"},"sceneLighting":true,"audioPlay":false,"sceneViewState":{"m_AlwaysRefresh":false,"showFog":true,"showSkybox":true,"showFlares":true,"showImageEffects":true,"showParticleSystems":true,"showVisualEffectGraphs":true,"m_FxEnabled":true},"in2DMode":false,"pivot":{"x":0.5835012793540955,"y":-0.5303457975387573,"z":-0.15389618277549745},"rotation":{"x":-0.09742854535579682,"y":0.8992204666137695,"z":-0.25790277123451235,"w":-0.33970072865486147},"size":3.4659831523895265,"orthographic":false}